bfdbhandler/__init__.py
bfdbhandler/dbhandler.py
BFPAPERdbhandler-0.0.dist-info/LICENSE
BFPAPERdbhandler-0.0.dist-info/METADATA
BFPAPERdbhandler-0.0.dist-info/WHEEL
BFPAPERdbhandler-0.0.dist-info/top_level.txt
BFPAPERdbhandler-0.0.dist-info/RECORD
