Metadata-Version: 2.1
Name: BFPAPERdbhandler
Version: 0.0
License-File: LICENSE
Requires-Dist: pandas (==1.4.4)
Requires-Dist: SQLAlchemy (==1.4.41)
